onesource/__init__.py
onesource/cli.py
onesource/operator.py
onesource-0.1.2.dist-info/METADATA
onesource-0.1.2.dist-info/WHEEL
onesource-0.1.2.dist-info/entry_points.txt
onesource-0.1.2.dist-info/top_level.txt
onesource-0.1.2.dist-info/RECORD
