Metadata-Version: 2.2
Name: onesource
Version: 0.1.2
Summary: Trigger marketing, sales and operations actions from git commits
Author: OneSource
Requires-Dist: click
Dynamic: author
Dynamic: requires-dist
Dynamic: summary
